setup.py
urequests.py
micropython_urequests.egg-info/PKG-INFO
micropython_urequests.egg-info/SOURCES.txt
micropython_urequests.egg-info/dependency_links.txt
micropython_urequests.egg-info/top_level.txt