Metadata-Version: 1.0
Name: micropython-urequests
Version: 0.5.2
Summary: urequests module for MicroPython
Home-page: https://github.com/micropython/micropython-lib
Author: micropython-lib Developers
Author-email: micro-python@googlegroups.com
License: MIT
Platform: UNKNOWN
